Workbook

Sheet Datos
A1: ID_Venta | B1: Fecha | C1: Producto | D1: Categoría | E1: Unidades | F1: Precio_Unitario | G1: Ciudad | H1: Canal | I1: Valoración | J1: Ingresos | K1: Coste | L1: Beneficio | M1: Vendedor | N1: Devolución
A2: 1001 | B2: 45352 | C2: Gafas de sol sport | D2: Accesorios | E2: 1 | F2: 25.5 | G2: Madrid | H2: App | I2: 4 | J2: 25.5 | K2: 10 | L2: 15.5 | M2: Ana García | N2: No
A3: 1002 | B3: 45353 | C3: Esterilla de Yoga | D3: Fitness | E3: 2 | F3: 18 | G3: Barcelona | H3: Web | I3: 5 | J3: 36 | K3: 14 | L3: 22 | M3: David Ruiz | N3: No
A4: 1003 | B4: 45354 | C4: Raqueta de Pádel | D4: Deportes | E4: 1 | F4: 85 | G4: Valencia | H4: Tienda | I4: 4 | J4: 85 | K4: 45 | L4: 40 | M4: Carlos López | N4: No
A5: 1004 | B5: 45356 | C5: Zapatillas de Running | D5: Calzado | E5: 1 | F5: 110 | G5: Sevilla | H5: Web | I5: 5 | J5: 110 | K5: 60 | L5: 50 | M5: Laura Martínez | N5: Sí
A6: 1005 | B6: 45358 | C6: Mancuernas 5kg (Par) | D6: Fitness | E6: 1 | F6: 35 | G6: Bilbao | H6: Tienda | I6: 4 | J6: 35 | K6: 15 | L6: 20 | M6: Marta Fernández | N6: No
A7: 1006 | B7: 45361 | C7: Reloj GPS Garmin | D7: Electrónica | E7: 1 | F7: 250 | G7: Madrid | H7: Web | I7: 5 | J7: 250 | K7: 180 | L7: 70 | M7: Ana García | N7: No
A8: 1007 | B8: 45363 | C8: Casco de Ciclismo | D8: Accesorios | E8: 1 | F8: 45 | G8: Barcelona | H8: App | I8: 3 | J8: 45 | K8: 20 | L8: 25 | M8: David Ruiz | N8: No
A9: 1008 | B9: 45366 | C9: Botella Térmica 1L | D9: Accesorios | E9: 3 | F9: 15 | G9: Valencia | H9: Tienda | I9: 4 | J9: 45 | K9: 18 | L9: 27 | M9: Carlos López | N9: No
A10: 1009 | B10: 45369 | C10: Saco de Boxeo | D10: Fitness | E10: 1 | F10: 90 | G10: Málaga | H10: Web | I10: 5 | J10: 90 | K10: 50 | L10: 40 | M10: Laura Martínez | N10: No
A11: 1010 | B11: 45371 | C11: Mochila de Senderismo | D11: Accesorios | E11: 2 | F11: 65 | G11: Bilbao | H11: Tienda | I11: 4 | J11: 130 | K11: 70 | L11: 60 | M11: Marta Fernández | N11: No
A12: 1011 | B12: 45373 | C12: Mallas Térmicas | D12: Ropa | E12: 1 | F12: 28 | G12: Madrid | H12: App | I12: 5 | J12: 28 | K12: 12 | L12: 30 | M12: Ana García | N12: No
A13: 1012 | B13: 45376 | C13: Auriculares Inalámbricos | D13: Electrónica | E13: 1 | F13: 55 | G13: Barcelona | H13: Web | I13: 2 | J13: 55 | K13: 25 | L13: 30 | M13: David Ruiz | N13: Sí
... A45: 1045 | B45: 45448 | C45: Zapatillas Halterofilia | D45: Cositas | E45: 5 | F45: 130 | G45: Madrid | H45: Web | I45: 5 | J45: 130 | K45: 80 | L45: 50 | M45: Marta Fernández | N45: No

Sheet Venta_por_categoria
A1: FILTRO | B1: Deportes
A3: {=_xlfn.CHOOSECOLS(_xlfn._xlws.FILTER(Datos!A:N,Datos!D:D=Venta_por_categoria!B1),3,4,5,10)} -> Raqueta de Pádel | B3: Deportes | C3: 1 | D3: 85
A4: Balón de Fútbol | B4: Deportes | C4: 4 | D4: 80
A5: Raqueta de Tenis | B5: Deportes | C5: 1 | D5: 120
A6: Bote Pelotas Pádel (Pack 3) | B6: Deportes | C6: 5 | D6: 30
A7: Muñequeras de Pádel | B7: Deportes | C7: 2 | D7: 16
A8: Neopreno Surf | B8: Deportes | C8: 1 | D8: 150
A9: Tabla de Paddle Surf | B9: Deportes | C9: 1 | D9: 300

Sheet venta por_categoria2
A1: FILTRO | B1: Accesorios
C4: {=_xlfn._xlws.FILTER(Datos!A:N,Datos!D:D='venta por_categoria2'!B1)} -> 1001 | D4: 45352 | E4: Gafas de sol sport | F4: Accesorios | G4: 1 | H4: 25.5 | I4: Madrid | J4: App | K4: 4 | L4: 25.5 | M4: 10 | N4: 15.5 | O4: Ana García | P4: No
C5: 1007 | D5: 45363 | E5: Casco de Ciclismo | F5: Accesorios | G5: 1 | H5: 45 | I5: Barcelona | J5: App | K5: 3 | L5: 45 | M5: 20 | N5: 25 | O5: David Ruiz | P5: No
C6: 1008 | D6: 45366 | E6: Botella Térmica 1L | F6: Accesorios | G6: 3 | H6: 15 | I6: Valencia | J6: Tienda | K6: 4 | L6: 45 | M6: 18 | N6: 27 | O6: Carlos López | P6: No
C7: 1010 | D7: 45371 | E7: Mochila de Senderismo | F7: Accesorios | G7: 2 | H7: 65 | I7: Bilbao | J7: Tienda | K7: 4 | L7: 130 | M7: 70 | N7: 60 | O7: Marta Fernández | P7: No
C8: 1017 | D8: 45387 | E8: Gafas de Natación | F8: Accesorios | G8: 2 | H8: 18 | I8: Barcelona | J8: Tienda | K8: 4 | L8: 36 | M8: 16 | N8: 20 | O8: David Ruiz | P8: No
C9: 1022 | D9: 45399 | E9: Bolsa de Deporte | F9: Accesorios | G9: 1 | H9: 35 | I9: Madrid | J9: Tienda | K9: 4 | L9: 35 | M9: 15 | N9: 20 | O9: David Ruiz | P9: No
C10: 1023 | D10: 45402 | E10: Gorra Transpirable | F10: Accesorios | G10: 2 | H10: 15 | I10: Barcelona | J10: Web | K10: 4 | L10: 30 | M10: 12 | N10: 18 | O10: Carlos López | P10: No
C11: 1027 | D11: 45414 | E11: Toalla de Microfibra | F11: Accesorios | G11: 3 | H11: 12 | I11: Málaga | J11: Tienda | K11: 5 | L11: 36 | M11: 15 | N11: 21 | O11: David Ruiz | P11: No
C12: 1030 | D12: 45422 | E12: Cinturón de Hidratación | F12: Accesorios | G12: 1 | H12: 22 | I12: Valencia | J12: Tienda | K12: 4 | L12: 22 | M12: 10 | N12: 12 | O12: Marta Fernández | P12: No
C13: 1036 | D13: 45437 | E13: Casco de Esquí | F13: Accesorios | G13: 1 | H13: 85 | I13: Valencia | J13: App | K13: 4 | L13: 85 | M13: 45 | N13: 40 | O13: Ana García | P13: No
C14: 1037 | D14: 45440 | E14: Gafas de Ventisca | F14: Accesorios | G14: 1 | H14: 50 | I14: Sevilla | J14: Web | K14: 4 | L14: 50 | M14: 25 | N14: 25 | O14: David Ruiz | P14: Sí

Sheet producto_estrella_ventas1
A1: ID_Venta | B1: Fecha | C1: Producto | D1: Categoría | E1: Unidades | F1: Precio_Unitario | G1: Ciudad | H1: Canal | I1: Valoración | J1: Ingresos | K1: Coste | L1: Beneficio | M1: Vendedor | N1: Devolución | P1: {=_xlfn.UNIQUE(D:D)} -> Categoría | Q1: Unidades totales incluida la devolucion | R1: Unidades vendidas sin devolucion
A2: 1022 | B2: 45399 | C2: Bolsa de Deporte | D2: Accesorios | E2: 1 | F2: 35 | G2: Madrid | H2: Tienda | I2: 4 | J2: 35 | K2: 15 | L2: 20 | M2: David Ruiz | N2: No | P2: Accesorios | Q2: =SUMIF(D:D,P2,E:E) -> 18 | R2: =SUMIFS(E:E,D:D,P2,N:N,"No") -> 17
A3: 1008 | B3: 45366 | C3: Botella Térmica 1L | D3: Accesorios | E3: 3 | F3: 15 | G3: Valencia | H3: Tienda | I3: 4 | J3: 45 | K3: 18 | L3: 27 | M3: Carlos López | N3: No | P3: Calzado | Q3: =SUMIF(D:D,P3,E:E) -> 3 | R3: =SUMIFS(E:E,D:D,P3,N:N,"No") -> 2
A4: 1007 | B4: 45363 | C4: Casco de Ciclismo | D4: Accesorios | E4: 1 | F4: 45 | G4: Barcelona | H4: App | I4: 3 | J4: 45 | K4: 20 | L4: 25 | M4: David Ruiz | N4: No | P4: Deportes | Q4: =SUMIF(D:D,P4,E:E) -> 15 | R4: =SUMIFS(E:E,D:D,P4,N:N,"No") -> 15
A5: 1036 | B5: 45437 | C5: Casco de Esquí | D5: Accesorios | E5: 1 | F5: 85 | G5: Valencia | H5: App | I5: 4 | J5: 85 | K5: 45 | L5: 40 | M5: Ana García | N5: No | P5: Electrónica | Q5: =SUMIF(D:D,P5,E:E) -> 3 | R5: =SUMIFS(E:E,D:D,P5,N:N,"No") -> 1
A6: 1030 | B6: 45422 | C6: Cinturón de Hidratación | D6: Accesorios | E6: 1 | F6: 22 | G6: Valencia | H6: Tienda | I6: 4 | J6: 22 | K6: 10 | L6: 12 | M6: Marta Fernández | N6: No | P6: Fitness | Q6: =SUMIF(D:D,P6,E:E) -> 15 | R6: =SUMIFS(E:E,D:D,P6,N:N,"No") -> 15
A7: 1017 | B7: 45387 | C7: Gafas de Natación | D7: Accesorios | E7: 2 | F7: 18 | G7: Barcelona | H7: Tienda | I7: 4 | J7: 36 | K7: 16 | L7: 20 | M7: David Ruiz | N7: No | P7: Ropa | Q7: =SUMIF(D:D,P7,E:E) -> 13 | R7: =SUMIFS(E:E,D:D,P7,N:N,"No") -> 12
A8: 1001 | B8: 45352 | C8: Gafas de sol sport | D8: Accesorios | E8: 1 | F8: 25.5 | G8: Madrid | H8: App | I8: 4 | J8: 25.5 | K8: 10 | L8: 15.5 | M8: Ana García | N8: No | P8: 0
A9: 1023 | B9: 45402 | C9: Gorra Transpirable | D9: Accesorios | E9: 2 | F9: 15 | G9: Barcelona | H9: Web | I9: 4 | J9: 30 | K9: 12 | L9: 18 | M9: Carlos López | N9: No
A10: 1010 | B10: 45371 | C10: Mochila de Senderismo | D10: Accesorios | E10: 2 | F10: 65 | G10: Bilbao | H10: Tienda | I10: 4 | J10: 130 | K10: 70 | L10: 60 | M10: Marta Fernández | N10: No
A11: 1027 | B11: 45414 | C11: Toalla de Microfibra | D11: Accesorios | E11: 3 | F11: 12 | G11: Málaga | H11: Tienda | I11: 5 | J11: 36 | K11: 15 | L11: 21 | M11: David Ruiz | N11: No
A12: 1018 | B12: 45390 | C12: Zapatillas de Trekking | D12: Calzado | E12: 1 | F12: 95 | G12: Valencia | H12: Web | I12: 4 | J12: 95 | K12: 55 | L12: 40 | M12: Carlos López | N12: No
A13: 1040 | B13: 45448 | C13: Zapatillas Halterofilia | D13: Calzado | E13: 1 | F13: 130 | G13: Madrid | H13: Web | I13: 5 | J13: 130 | K13: 80 | L13: 50 | M13: Marta Fernández | N13: No
A14: 1013 | B14: 45378 | C14: Balón de Fútbol | D14: Deportes | E14: 4 | F14: 20 | G14: Sevilla | H14: Tienda | I14: 4 | J14: 80 | K14: 32 | L14: 48 | M14: Carlos López | N14: No
A15: 1026 | B15: 45410 | C15: Bote Pelotas Pádel (Pack 3) | D15: Deportes | E15: 5 | F15: 6 | G15: Bilbao | H15: Web | I15: 4 | J15: 30 | K15: 15 | L15: 15 | M15: Ana García | N15: No
A16: 1031 | B16: 45424 | C16: Muñequeras de Pádel | D16: Deportes | E16: 2 | F16: 8 | G16: Sevilla | H16: Web | I16: 3 | J16: 16 | K16: 6 | L16: 10 | M16: Ana García | N16: No
A17: 1034 | B17: 45432 | C17: Neopreno Surf | D17: Deportes | E17: 1 | F17: 150 | G17: Madrid | H17: Web | I17: 4 | J17: 150 | K17: 90 | L17: 60 | M17: Laura Martínez | N17: No
A18: 1003 | B18: 45354 | C18: Raqueta de Pádel | D18: Deportes | E18: 1 | F18: 85 | G18: Valencia | H18: Tienda | I18: 4 | J18: 85 | K18: 45 | L18: 40 | M18: Carlos López | N18: No
A19: 1025 | B19: 45407 | C19: Raqueta de Tenis | D19: Deportes | E19: 1 | F19: 120 | G19: Sevilla | H19: Tienda | I19: 5 | J19: 120 | K19: 70 | L19: 50 | M19: Marta Fernández | N19: No
A20: 1035 | B20: 45434 | C20: Tabla de Paddle Surf | D20: Deportes | E20: 1 | F20: 300 | G20: Barcelona | H20: Tienda | I20: 5 | J20: 300 | K20: 180 | L20: 120 | M20: Marta Fernández | N20: No
... A41: 1028 | B41: 45417 | C41: Pantalón de Chándal | D41: Ropa | E41: 1 | F41: 30 | G41: Madrid | H41: Web | I41: 4 | J41: 30 | K41: 14 | L41: 16 | M41: Carlos López | N41: Sí

Sheet producto_estrella2
A1: Categoria | B1: Unidades Totales
A2: {=_xlfn.UNIQUE(Tabla2[Categoría])} -> Accesorios | B2: =SUMIFS(Tabla2[Unidades],Tabla2[Categoría],producto_estrella2!A2,Tabla2[Devolución],"No") -> 17
A3: Fitness | B3: =SUMIFS(Tabla2[Unidades],Tabla2[Categoría],producto_estrella2!A3,Tabla2[Devolución],"No") -> 15
A4: Deportes | B4: =SUMIFS(Tabla2[Unidades],Tabla2[Categoría],producto_estrella2!A4,Tabla2[Devolución],"No") -> 15
A5: Calzado | B5: =SUMIFS(Tabla2[Unidades],Tabla2[Categoría],producto_estrella2!A5,Tabla2[Devolución],"No") -> 2
A6: Electrónica | B6: =SUMIFS(Tabla2[Unidades],Tabla2[Categoría],producto_estrella2!A6,Tabla2[Devolución],"No") -> 1
A7: Ropa | B7: =SUMIFS(Tabla2[Unidades],Tabla2[Categoría],producto_estrella2!A7,Tabla2[Devolución],"No") -> 12
A8: Material | B8: =SUMIFS(Tabla2[Unidades],Tabla2[Categoría],producto_estrella2!A8,Tabla2[Devolución],"No") -> 6
A9: Cositas | B9: =SUMIFS(Tabla2[Unidades],Tabla2[Categoría],producto_estrella2!A9,Tabla2[Devolución],"No") -> 10

Sheet Datos1
A1: ID_Venta | B1: Columna1 | C1: Producto | D1: Categoría | E1: Unidades | F1: Precio_Unitario | G1: Ciudad | H1: Canal | I1: Valoración | J1: Ingresos | K1: Coste | L1: Beneficio | M1: Vendedor | N1: Devolución
A2: 1022 | B2: 45399 | C2: Bolsa de Deporte | D2: Accesorios | E2: 5 | F2: 35 | G2: Madrid | H2: Tienda | I2: 4 | J2: 35 | K2: 15 | L2: 20 | M2: David Ruiz | N2: No
A3: 1008 | B3: 45366 | C3: Botella Térmica 1L | D3: Accesorios | E3: 3 | F3: 15 | G3: Valencia | H3: Tienda | I3: 4 | J3: 45 | K3: 18 | L3: 27 | M3: Carlos López | N3: No
A4: 1007 | B4: 45363 | C4: Casco de Ciclismo | D4: Accesorios | E4: 1 | F4: 45 | G4: Barcelona | H4: App | I4: 3 | J4: 45 | K4: 20 | L4: 25 | M4: David Ruiz | N4: No
A5: 1036 | B5: 45437 | C5: Casco de Esquí | D5: Accesorios | E5: 6 | F5: 85 | G5: Valencia | H5: App | I5: 4 | J5: 85 | K5: 45 | L5: 40 | M5: Ana García | N5: No
A6: 1030 | B6: 45422 | C6: Cinturón de Hidratación | D6: Accesorios | E6: 1 | F6: 22 | G6: Valencia | H6: Tienda | I6: 4 | J6: 22 | K6: 10 | L6: 12 | M6: Marta Fernández | N6: No
A7: 1017 | B7: 45387 | C7: Gafas de Natación | D7: Accesorios | E7: 2 | F7: 18 | G7: Barcelona | H7: Tienda | I7: 4 | J7: 36 | K7: 16 | L7: 20 | M7: David Ruiz | N7: No
A8: 1001 | B8: 45352 | C8: Gafas de sol sport | D8: Accesorios | E8: 1 | F8: 25.5 | G8: Madrid | H8: App | I8: 4 | J8: 25.5 | K8: 10 | L8: 15.5 | M8: Ana García | N8: No
A9: 1023 | B9: 45402 | C9: Gorra Transpirable | D9: Accesorios | E9: 9 | F9: 15 | G9: Barcelona | H9: Web | I9: 4 | J9: 30 | K9: 12 | L9: 18 | M9: Carlos López | N9: No
A10: 1010 | B10: 45371 | C10: Mochila de Senderismo | D10: Accesorios | E10: 2 | F10: 65 | G10: Bilbao | H10: Tienda | I10: 4 | J10: 130 | K10: 70 | L10: 60 | M10: Marta Fernández | N10: No
A11: 1027 | B11: 45414 | C11: Toalla de Microfibra | D11: Accesorios | E11: 3 | F11: 12 | G11: Málaga | H11: Tienda | I11: 5 | J11: 36 | K11: 15 | L11: 21 | M11: David Ruiz | N11: No
A12: 1037 | B12: 45440 | C12: Gafas de Ventisca | D12: Accesorios | E12: 1 | F12: 50 | G12: Sevilla | H12: Web | I12: 4 | J12: 50 | K12: 25 | L12: 25 | M12: David Ruiz | N12: Sí
A13: 1018 | B13: 45390 | C13: Zapatillas de Trekking | D13: Calzado | E13: 5 | F13: 95 | G13: Valencia | H13: Web | I13: 4 | J13: 95 | K13: 55 | L13: 40 | M13: Carlos López | N13: No
... A41: 1028 | B41: 45417 | C41: Pantalón de Chándal | D41: Ropa | E41: 40 | F41: 30 | G41: Madrid | H41: Web | I41: 4 | J41: 30 | K41: 14 | L41: 16 | M41: Carlos López | N41: Sí

Sheet Hoja1
A1: Accesorios | C1: Calzado | E1: Deportes | G1: Electrónica | I1: Fitness | K1: Ropa
A2: Producto | B2: Ventas en Unidades | C2: Producto | D2: Ventas en Unidades | E2: Producto | F2: Ventas en Unidades | G2: Producto | H2: Ventas en Unidades | I2: Producto | J2: Ventas en Unidades | K2: Producto | L2: Ventas en Unidades
A3: {=_xlfn.CHOOSECOLS(_xlfn._xlws.FILTER(Datos1[[Producto]:[Unidades]],Datos1[Categoría]=Hoja1!A1),1,3)} -> Bolsa de Deporte | B3: 5 | C3: {=_xlfn.CHOOSECOLS(_xlfn._xlws.FILTER(Datos1[[Producto]:[Unidades]],Datos1[Categoría]=Hoja1!C1),1,3)} -> Zapatillas de Trekking | D3: 5 | E3: {=_xlfn.CHOOSECOLS(_xlfn._xlws.FILTER(Datos1[[Producto]:[Unidades]],Datos1[Categoría]=Hoja1!E1),1,3)} -> Balón de Fútbol | F3: 11 | G3: {=_xlfn.CHOOSECOLS(_xlfn._xlws.FILTER(Datos1[[Producto]:[Unidades]],Datos1[Categoría]=Hoja1!G1),1,3)} -> Reloj GPS Garmin | H3: 5 | I3: {=_xlfn.CHOOSECOLS(_xlfn._xlws.FILTER(Datos1[[Producto]:[Unidades]],Datos1[Categoría]=Hoja1!I1),1,3)} -> Banda Elástica Resistencia | J3: 3 | K3: {=_xlfn.CHOOSECOLS(_xlfn._xlws.FILTER(Datos1[[Producto]:[Unidades]],Datos1[Categoría]=Hoja1!K1),1,3)} -> Calcetines Running (Pack 3) | L3: 30
A4: Botella Térmica 1L | B4: 3 | C4: Zapatillas Halterofilia | D4: 1 | E4: Bote Pelotas Pádel (Pack 3) | F4: 5 | G4: Auriculares Inalámbricos | H4: 2 | I4: Cuerda de Saltar | J4: 5 | K4: Camiseta Térmica | L4: 25
A5: Casco de Ciclismo | B5: 1 | C5: Zapatillas de Running | D5: 10 | E5: Muñequeras de Pádel | F5: 2 | G5: Pulsómetro de Pecho | H5: 1 | I5: Esterilla de Yoga | J5: 20 | K5: Cortavientos Ligero | L5: 1
A6: Casco de Esquí | B6: 6 | E6: Neopreno Surf | F6: 1 | I6: Guantes de Gimnasio | J6: 1 | K6: Maillot de Ciclismo | L6: 5
A7: Cinturón de Hidratación | B7: 1 | E7: Raqueta de Pádel | F7: 7 | I7: Mancuernas 5kg (Par) | J7: 5 | K7: Mallas de Compresión | L7: 3
A8: Gafas de Natación | B8: 2 | E8: Raqueta de Tenis | F8: 8 | I8: Pesa Rusa 8kg | J8: 2 | K8: Mallas Térmicas | L8: 2
A9: Gafas de sol sport | B9: 1 | E9: Tabla de Paddle Surf | F9: 1 | I9: Rodillo de Masaje (Foam) | J9: 20 | K9: Sujetador Deportivo | L9: 10
A10: Gorra Transpirable | B10: 9 | I10: Saco de Boxeo | J10: 8 | K10: Pantalón de Chándal | L10: 40
A11: Mochila de Senderismo | B11: 2
A12: Toalla de Microfibra | B12: 3
A13: Gafas de Ventisca | B13: 1
